{
  "semantic-text": {
    "header-xl": {
      "padding-top": {
        "sm": {
          "value": "{spacing.0}",
          "type": "number"
        },
        "md": {
          "value": "{spacing.0}",
          "type": "number"
        },
        "lg": {
          "value": "{spacing.0}",
          "type": "number"
        },
        "xl": {
          "value": "{spacing.0}",
          "type": "number"
        }
      },
      "padding-bottom": {
        "sm": {
          "value": "{spacing.150}",
          "type": "number"
        },
        "md": {
          "value": "{spacing.150}",
          "type": "number"
        },
        "lg": {
          "value": "{spacing.200}",
          "type": "number"
        },
        "xl": {
          "value": "{spacing.200}",
          "type": "number"
        }
      },
      "typography-params": {
        "style": {
          "sm": {
            "value": "display",
            "type": "other",
            "description": "figma-only"
          },
          "md": {
            "value": "display",
            "type": "other",
            "description": "figma-only"
          },
          "lg": {
            "value": "display",
            "type": "other",
            "description": "figma-only"
          },
          "xl": {
            "value": "display",
            "type": "other",
            "description": "figma-only"
          }
        },
        "size": {
          "sm": {
            "value": "500",
            "type": "other",
            "description": "figma-only"
          },
          "md": {
            "value": "500",
            "type": "other",
            "description": "figma-only"
          },
          "lg": {
            "value": "600",
            "type": "other",
            "description": "figma-only"
          },
          "xl": {
            "value": "700",
            "type": "other",
            "description": "figma-only"
          }
        },
        "category": {
          "sm": {
            "value": "accent",
            "type": "other",
            "description": "figma-only"
          },
          "md": {
            "value": "accent",
            "type": "other",
            "description": "figma-only"
          },
          "lg": {
            "value": "accent",
            "type": "other",
            "description": "figma-only"
          },
          "xl": {
            "value": "accent",
            "type": "other",
            "description": "figma-only"
          }
        }
      },
      "typography": {
        "sm": {
          "value": "{semantic-text.header-xl.typography-params.style.sm}.{semantic-text.header-xl.typography-params.size.sm}.{semantic-text.header-xl.typography-params.category.sm}",
          "type": "other"
        },
        "md": {
          "value": "{semantic-text.header-xl.typography-params.style.md}.{semantic-text.header-xl.typography-params.size.md}.{semantic-text.header-xl.typography-params.category.md}",
          "type": "other"
        },
        "lg": {
          "value": "{semantic-text.header-xl.typography-params.style.lg}.{semantic-text.header-xl.typography-params.size.lg}.{semantic-text.header-xl.typography-params.category.lg}",
          "type": "other"
        },
        "xl": {
          "value": "{semantic-text.header-xl.typography-params.style.xl}.{semantic-text.header-xl.typography-params.size.xl}.{semantic-text.header-xl.typography-params.category.xl}",
          "type": "other"
        }
      }
    },
    "header-l": {
      "padding-top": {
        "sm": {
          "value": "{spacing.50}",
          "type": "number"
        },
        "md": {
          "value": "{spacing.50}",
          "type": "number"
        },
        "lg": {
          "value": "{spacing.50}",
          "type": "number"
        },
        "xl": {
          "value": "{spacing.100}",
          "type": "number"
        }
      },
      "padding-bottom": {
        "sm": {
          "value": "{spacing.200}",
          "type": "number"
        },
        "md": {
          "value": "{spacing.200}",
          "type": "number"
        },
        "lg": {
          "value": "{spacing.200}",
          "type": "number"
        },
        "xl": {
          "value": "{spacing.200}",
          "type": "number"
        }
      },
      "typography-params": {
        "style": {
          "sm": {
            "value": "display",
            "type": "other",
            "description": "figma-only"
          },
          "md": {
            "value": "display",
            "type": "other",
            "description": "figma-only"
          },
          "lg": {
            "value": "display",
            "type": "other",
            "description": "figma-only"
          },
          "xl": {
            "value": "display",
            "type": "other",
            "description": "figma-only"
          }
        },
        "size": {
          "sm": {
            "value": "450",
            "type": "other",
            "description": "figma-only"
          },
          "md": {
            "value": "450",
            "type": "other",
            "description": "figma-only"
          },
          "lg": {
            "value": "500",
            "type": "other",
            "description": "figma-only"
          },
          "xl": {
            "value": "600",
            "type": "other",
            "description": "figma-only"
          }
        },
        "category": {
          "sm": {
            "value": "accent",
            "type": "other",
            "description": "figma-only"
          },
          "md": {
            "value": "accent",
            "type": "other",
            "description": "figma-only"
          },
          "lg": {
            "value": "accent",
            "type": "other",
            "description": "figma-only"
          },
          "xl": {
            "value": "accent",
            "type": "other",
            "description": "figma-only"
          }
        }
      },
      "typography": {
        "sm": {
          "value": "{semantic-text.header-l.typography-params.style.sm}.{semantic-text.header-l.typography-params.size.sm}.{semantic-text.header-l.typography-params.category.sm}",
          "type": "other"
        },
        "md": {
          "value": "{semantic-text.header-l.typography-params.style.md}.{semantic-text.header-l.typography-params.size.md}.{semantic-text.header-l.typography-params.category.md}",
          "type": "other"
        },
        "lg": {
          "value": "{semantic-text.header-l.typography-params.style.lg}.{semantic-text.header-l.typography-params.size.lg}.{semantic-text.header-l.typography-params.category.lg}",
          "type": "other"
        },
        "xl": {
          "value": "{semantic-text.header-l.typography-params.style.xl}.{semantic-text.header-l.typography-params.size.xl}.{semantic-text.header-l.typography-params.category.xl}",
          "type": "other"
        }
      }
    },
    "header-m": {
      "padding-top": {
        "sm": {
          "value": "{spacing.100}",
          "type": "number"
        },
        "md": {
          "value": "{spacing.100}",
          "type": "number"
        },
        "lg": {
          "value": "{spacing.100}",
          "type": "number"
        },
        "xl": {
          "value": "{spacing.100}",
          "type": "number"
        }
      },
      "padding-bottom": {
        "sm": {
          "value": "{spacing.200}",
          "type": "number"
        },
        "md": {
          "value": "{spacing.200}",
          "type": "number"
        },
        "lg": {
          "value": "{spacing.200}",
          "type": "number"
        },
        "xl": {
          "value": "{spacing.200}",
          "type": "number"
        }
      },
      "typography-params": {
        "style": {
          "sm": {
            "value": "display",
            "type": "other",
            "description": "figma-only"
          },
          "md": {
            "value": "display",
            "type": "other",
            "description": "figma-only"
          },
          "lg": {
            "value": "display",
            "type": "other",
            "description": "figma-only"
          },
          "xl": {
            "value": "display",
            "type": "other",
            "description": "figma-only"
          }
        },
        "size": {
          "sm": {
            "value": "400",
            "type": "other",
            "description": "figma-only"
          },
          "md": {
            "value": "400",
            "type": "other",
            "description": "figma-only"
          },
          "lg": {
            "value": "450",
            "type": "other",
            "description": "figma-only"
          },
          "xl": {
            "value": "500",
            "type": "other",
            "description": "figma-only"
          }
        },
        "category": {
          "sm": {
            "value": "accent",
            "type": "other",
            "description": "figma-only"
          },
          "md": {
            "value": "accent",
            "type": "other",
            "description": "figma-only"
          },
          "lg": {
            "value": "accent",
            "type": "other",
            "description": "figma-only"
          },
          "xl": {
            "value": "accent",
            "type": "other",
            "description": "figma-only"
          }
        }
      },
      "typography": {
        "sm": {
          "value": "{semantic-text.header-m.typography-params.style.sm}.{semantic-text.header-m.typography-params.size.sm}.{semantic-text.header-m.typography-params.category.sm}",
          "type": "other"
        },
        "md": {
          "value": "{semantic-text.header-m.typography-params.style.md}.{semantic-text.header-m.typography-params.size.md}.{semantic-text.header-m.typography-params.category.md}",
          "type": "other"
        },
        "lg": {
          "value": "{semantic-text.header-m.typography-params.style.lg}.{semantic-text.header-m.typography-params.size.lg}.{semantic-text.header-m.typography-params.category.lg}",
          "type": "other"
        },
        "xl": {
          "value": "{semantic-text.header-m.typography-params.style.xl}.{semantic-text.header-m.typography-params.size.xl}.{semantic-text.header-m.typography-params.category.xl}",
          "type": "other"
        }
      }
    },
    "header-s": {
      "padding-top": {
        "sm": {
          "value": "{spacing.150}",
          "type": "number"
        },
        "md": {
          "value": "{spacing.150}",
          "type": "number"
        },
        "lg": {
          "value": "{spacing.50}",
          "type": "number"
        },
        "xl": {
          "value": "{spacing.100}",
          "type": "number"
        }
      },
      "padding-bottom": {
        "sm": {
          "value": "{spacing.250}",
          "type": "number"
        },
        "md": {
          "value": "{spacing.250}",
          "type": "number"
        },
        "lg": {
          "value": "{spacing.200}",
          "type": "number"
        },
        "xl": {
          "value": "{spacing.200}",
          "type": "number"
        }
      },
      "typography-params": {
        "style": {
          "sm": {
            "value": "display",
            "type": "other",
            "description": "figma-only"
          },
          "md": {
            "value": "display",
            "type": "other",
            "description": "figma-only"
          },
          "lg": {
            "value": "display",
            "type": "other",
            "description": "figma-only"
          },
          "xl": {
            "value": "display",
            "type": "other",
            "description": "figma-only"
          }
        },
        "size": {
          "sm": {
            "value": "350",
            "type": "other",
            "description": "figma-only"
          },
          "md": {
            "value": "350",
            "type": "other",
            "description": "figma-only"
          },
          "lg": {
            "value": "400",
            "type": "other",
            "description": "figma-only"
          },
          "xl": {
            "value": "450",
            "type": "other",
            "description": "figma-only"
          }
        },
        "category": {
          "sm": {
            "value": "accent",
            "type": "other",
            "description": "figma-only"
          },
          "md": {
            "value": "accent",
            "type": "other",
            "description": "figma-only"
          },
          "lg": {
            "value": "accent",
            "type": "other",
            "description": "figma-only"
          },
          "xl": {
            "value": "accent",
            "type": "other",
            "description": "figma-only"
          }
        }
      },
      "typography": {
        "sm": {
          "value": "{semantic-text.header-s.typography-params.style.sm}.{semantic-text.header-s.typography-params.size.sm}.{semantic-text.header-s.typography-params.category.sm}",
          "type": "other"
        },
        "md": {
          "value": "{semantic-text.header-s.typography-params.style.md}.{semantic-text.header-s.typography-params.size.md}.{semantic-text.header-s.typography-params.category.md}",
          "type": "other"
        },
        "lg": {
          "value": "{semantic-text.header-s.typography-params.style.lg}.{semantic-text.header-s.typography-params.size.lg}.{semantic-text.header-s.typography-params.category.lg}",
          "type": "other"
        },
        "xl": {
          "value": "{semantic-text.header-s.typography-params.style.xl}.{semantic-text.header-s.typography-params.size.xl}.{semantic-text.header-s.typography-params.category.xl}",
          "type": "other"
        }
      }
    },
    "header-xs": {
      "padding-top": {
        "sm": {
          "value": "{spacing.150}",
          "type": "number"
        },
        "md": {
          "value": "{spacing.150}",
          "type": "number"
        },
        "lg": {
          "value": "{spacing.50}",
          "type": "number"
        },
        "xl": {
          "value": "{spacing.100}",
          "type": "number"
        }
      },
      "padding-bottom": {
        "sm": {
          "value": "{spacing.250}",
          "type": "number"
        },
        "md": {
          "value": "{spacing.250}",
          "type": "number"
        },
        "lg": {
          "value": "{spacing.250}",
          "type": "number"
        },
        "xl": {
          "value": "{spacing.250}",
          "type": "number"
        }
      },
      "typography-params": {
        "style": {
          "sm": {
            "value": "compact",
            "type": "other",
            "description": "figma-only"
          },
          "md": {
            "value": "compact",
            "type": "other",
            "description": "figma-only"
          },
          "lg": {
            "value": "display",
            "type": "other",
            "description": "figma-only"
          },
          "xl": {
            "value": "display",
            "type": "other",
            "description": "figma-only"
          }
        },
        "size": {
          "sm": {
            "value": "300",
            "type": "other",
            "description": "figma-only"
          },
          "md": {
            "value": "300",
            "type": "other",
            "description": "figma-only"
          },
          "lg": {
            "value": "350",
            "type": "other",
            "description": "figma-only"
          },
          "xl": {
            "value": "400",
            "type": "other",
            "description": "figma-only"
          }
        },
        "category": {
          "sm": {
            "value": "accent",
            "type": "other",
            "description": "figma-only"
          },
          "md": {
            "value": "accent",
            "type": "other",
            "description": "figma-only"
          },
          "lg": {
            "value": "accent",
            "type": "other",
            "description": "figma-only"
          },
          "xl": {
            "value": "accent",
            "type": "other",
            "description": "figma-only"
          }
        }
      },
      "typography": {
        "sm": {
          "value": "{semantic-text.header-xs.typography-params.style.sm}.{semantic-text.header-xs.typography-params.size.sm}.{semantic-text.header-xs.typography-params.category.sm}",
          "type": "other"
        },
        "md": {
          "value": "{semantic-text.header-xs.typography-params.style.md}.{semantic-text.header-xs.typography-params.size.md}.{semantic-text.header-xs.typography-params.category.md}",
          "type": "other"
        },
        "lg": {
          "value": "{semantic-text.header-xs.typography-params.style.lg}.{semantic-text.header-xs.typography-params.size.lg}.{semantic-text.header-xs.typography-params.category.lg}",
          "type": "other"
        },
        "xl": {
          "value": "{semantic-text.header-xs.typography-params.style.xl}.{semantic-text.header-xs.typography-params.size.xl}.{semantic-text.header-xs.typography-params.category.xl}",
          "type": "other"
        }
      }
    },
    "paragraph-l": {
      "padding-top": {
        "sm": {
          "value": "{spacing.100}",
          "type": "number"
        },
        "md": {
          "value": "{spacing.100}",
          "type": "number"
        },
        "lg": {
          "value": "{spacing.100}",
          "type": "number"
        },
        "xl": {
          "value": "{spacing.100}",
          "type": "number"
        }
      },
      "padding-bottom": {
        "sm": {
          "value": "{spacing.200}",
          "type": "number"
        },
        "md": {
          "value": "{spacing.200}",
          "type": "number"
        },
        "lg": {
          "value": "{spacing.200}",
          "type": "number"
        },
        "xl": {
          "value": "{spacing.200}",
          "type": "number"
        }
      },
      "typography-params": {
        "style": {
          "sm": {
            "value": "text",
            "type": "other",
            "description": "figma-only"
          },
          "md": {
            "value": "text",
            "type": "other",
            "description": "figma-only"
          },
          "lg": {
            "value": "text",
            "type": "other",
            "description": "figma-only"
          },
          "xl": {
            "value": "text",
            "type": "other",
            "description": "figma-only"
          }
        },
        "size": {
          "sm": {
            "value": "350",
            "type": "other",
            "description": "figma-only"
          },
          "md": {
            "value": "350",
            "type": "other",
            "description": "figma-only"
          },
          "lg": {
            "value": "400",
            "type": "other",
            "description": "figma-only"
          },
          "xl": {
            "value": "400",
            "type": "other",
            "description": "figma-only"
          }
        },
        "category": {
          "sm": {
            "value": "default",
            "type": "other",
            "description": "figma-only"
          },
          "md": {
            "value": "default",
            "type": "other",
            "description": "figma-only"
          },
          "lg": {
            "value": "default",
            "type": "other",
            "description": "figma-only"
          },
          "xl": {
            "value": "default",
            "type": "other",
            "description": "figma-only"
          }
        }
      },
      "typography": {
        "sm": {
          "value": "{semantic-text.paragraph-l.typography-params.style.sm}.{semantic-text.paragraph-l.typography-params.size.sm}.{semantic-text.paragraph-l.typography-params.category.sm}",
          "type": "other"
        },
        "md": {
          "value": "{semantic-text.paragraph-l.typography-params.style.md}.{semantic-text.paragraph-l.typography-params.size.md}.{semantic-text.paragraph-l.typography-params.category.md}",
          "type": "other"
        },
        "lg": {
          "value": "{semantic-text.paragraph-l.typography-params.style.lg}.{semantic-text.paragraph-l.typography-params.size.lg}.{semantic-text.paragraph-l.typography-params.category.lg}",
          "type": "other"
        },
        "xl": {
          "value": "{semantic-text.paragraph-l.typography-params.style.xl}.{semantic-text.paragraph-l.typography-params.size.xl}.{semantic-text.paragraph-l.typography-params.category.xl}",
          "type": "other"
        }
      }
    },
    "paragraph-m": {
      "padding-top": {
        "sm": {
          "value": "{spacing.0}",
          "type": "number"
        },
        "md": {
          "value": "{spacing.0}",
          "type": "number"
        },
        "lg": {
          "value": "{spacing.100}",
          "type": "number"
        },
        "xl": {
          "value": "{spacing.100}",
          "type": "number"
        }
      },
      "padding-bottom": {
        "sm": {
          "value": "{spacing.100}",
          "type": "number"
        },
        "md": {
          "value": "{spacing.100}",
          "type": "number"
        },
        "lg": {
          "value": "{spacing.200}",
          "type": "number"
        },
        "xl": {
          "value": "{spacing.200}",
          "type": "number"
        }
      },
      "typography-params": {
        "style": {
          "sm": {
            "value": "text",
            "type": "other",
            "description": "figma-only"
          },
          "md": {
            "value": "text",
            "type": "other",
            "description": "figma-only"
          },
          "lg": {
            "value": "text",
            "type": "other",
            "description": "figma-only"
          },
          "xl": {
            "value": "text",
            "type": "other",
            "description": "figma-only"
          }
        },
        "size": {
          "sm": {
            "value": "300",
            "type": "other",
            "description": "figma-only"
          },
          "md": {
            "value": "300",
            "type": "other",
            "description": "figma-only"
          },
          "lg": {
            "value": "350",
            "type": "other",
            "description": "figma-only"
          },
          "xl": {
            "value": "350",
            "type": "other",
            "description": "figma-only"
          }
        },
        "category": {
          "sm": {
            "value": "default",
            "type": "other",
            "description": "figma-only"
          },
          "md": {
            "value": "default",
            "type": "other",
            "description": "figma-only"
          },
          "lg": {
            "value": "default",
            "type": "other",
            "description": "figma-only"
          },
          "xl": {
            "value": "default",
            "type": "other",
            "description": "figma-only"
          }
        }
      },
      "typography": {
        "sm": {
          "value": "{semantic-text.paragraph-m.typography-params.style.sm}.{semantic-text.paragraph-m.typography-params.size.sm}.{semantic-text.paragraph-m.typography-params.category.sm}",
          "type": "other"
        },
        "md": {
          "value": "{semantic-text.paragraph-m.typography-params.style.md}.{semantic-text.paragraph-m.typography-params.size.md}.{semantic-text.paragraph-m.typography-params.category.md}",
          "type": "other"
        },
        "lg": {
          "value": "{semantic-text.paragraph-m.typography-params.style.lg}.{semantic-text.paragraph-m.typography-params.size.lg}.{semantic-text.paragraph-m.typography-params.category.lg}",
          "type": "other"
        },
        "xl": {
          "value": "{semantic-text.paragraph-m.typography-params.style.xl}.{semantic-text.paragraph-m.typography-params.size.xl}.{semantic-text.paragraph-m.typography-params.category.xl}",
          "type": "other"
        }
      }
    },
    "paragraph-s": {
      "padding-top": {
        "sm": {
          "value": "{spacing.0}",
          "type": "number"
        },
        "md": {
          "value": "{spacing.0}",
          "type": "number"
        },
        "lg": {
          "value": "{spacing.0}",
          "type": "number"
        },
        "xl": {
          "value": "{spacing.0}",
          "type": "number"
        }
      },
      "padding-bottom": {
        "sm": {
          "value": "{spacing.100}",
          "type": "number"
        },
        "md": {
          "value": "{spacing.100}",
          "type": "number"
        },
        "lg": {
          "value": "{spacing.100}",
          "type": "number"
        },
        "xl": {
          "value": "{spacing.100}",
          "type": "number"
        }
      },
      "typography-params": {
        "style": {
          "sm": {
            "value": "text",
            "type": "other",
            "description": "figma-only"
          },
          "md": {
            "value": "text",
            "type": "other",
            "description": "figma-only"
          },
          "lg": {
            "value": "text",
            "type": "other",
            "description": "figma-only"
          },
          "xl": {
            "value": "text",
            "type": "other",
            "description": "figma-only"
          }
        },
        "size": {
          "sm": {
            "value": "250",
            "type": "other",
            "description": "figma-only"
          },
          "md": {
            "value": "250",
            "type": "other",
            "description": "figma-only"
          },
          "lg": {
            "value": "300",
            "type": "other",
            "description": "figma-only"
          },
          "xl": {
            "value": "300",
            "type": "other",
            "description": "figma-only"
          }
        },
        "category": {
          "sm": {
            "value": "default",
            "type": "other",
            "description": "figma-only"
          },
          "md": {
            "value": "default",
            "type": "other",
            "description": "figma-only"
          },
          "lg": {
            "value": "default",
            "type": "other",
            "description": "figma-only"
          },
          "xl": {
            "value": "default",
            "type": "other",
            "description": "figma-only"
          }
        }
      },
      "typography": {
        "sm": {
          "value": "{semantic-text.paragraph-s.typography-params.style.sm}.{semantic-text.paragraph-s.typography-params.size.sm}.{semantic-text.paragraph-s.typography-params.category.sm}",
          "type": "other"
        },
        "md": {
          "value": "{semantic-text.paragraph-s.typography-params.style.md}.{semantic-text.paragraph-s.typography-params.size.md}.{semantic-text.paragraph-s.typography-params.category.md}",
          "type": "other"
        },
        "lg": {
          "value": "{semantic-text.paragraph-s.typography-params.style.lg}.{semantic-text.paragraph-s.typography-params.size.lg}.{semantic-text.paragraph-s.typography-params.category.lg}",
          "type": "other"
        },
        "xl": {
          "value": "{semantic-text.paragraph-s.typography-params.style.xl}.{semantic-text.paragraph-s.typography-params.size.xl}.{semantic-text.paragraph-s.typography-params.category.xl}",
          "type": "other"
        }
      }
    }
  }
}