{
  "main-layout": {
    "breakpoint": {
      "value": "tablet-landscape",
      "type": "text",
      "description": "figma-only"
    },
    "min-width": {
      "value": "{layout.breakpoint.lg}",
      "type": "number"
    },
    "max-width": {
      "value": "{layout.max-width.lg}",
      "type": "number"
    },
    "width": {
      "value": "{product.width.lg}",
      "type": "number",
      "description": "figma-only"
    },
    "height": {
      "value": "{product.height.lg}",
      "type": "number",
      "description": "figma-only"
    },
    "col-number": {
      "value": "{layout.col-number.lg}",
      "type": "number"
    },
    "col-width": {
      "value": "{layout.col-width.lg}",
      "type": "number"
    },
    "gutter": {
      "value": "{layout.gutter.lg}",
      "type": "number"
    },
    "margin-horizontal": {
      "value": "{spacing.700}",
      "type": "number"
    },
    "content-compensation": {
      "value": "{spacing.0}",
      "type": "number"
    },
    "ignore-margin-horizontal": {
      "value": "-{main-layout.margin-horizontal}",
      "type": "number",
      "description": "figma-only"
    }
  }
}